{
  "hash": "f572d094",
  "configHash": "b597be49",
  "lockfileHash": "4067fd0c",
  "browserHash": "d7b67ab8",
  "optimized": {
    "vue": {
      "src": "../../../../node_modules/.pnpm/vue@3.4.29/node_modules/vue/dist/vue.runtime.esm-bundler.js",
      "file": "vue.js",
      "fileHash": "eae864d3",
      "needsInterop": false
    },
    "vitepress > @vue/devtools-api": {
      "src": "../../../../node_modules/.pnpm/@vue+devtools-api@7.3.2/node_modules/@vue/devtools-api/dist/index.js",
      "file": "vitepress___@vue_devtools-api.js",
      "fileHash": "07cacb63",
      "needsInterop": false
    },
    "vitepress > @vueuse/core": {
      "src": "../../../../node_modules/.pnpm/@vueuse+core@10.11.0_vue@3.4.29/node_modules/@vueuse/core/index.mjs",
      "file": "vitepress___@vueuse_core.js",
      "fileHash": "4b5e70d4",
      "needsInterop": false
    },
    "vitepress > @vueuse/integrations/useFocusTrap": {
      "src": "../../../../node_modules/.pnpm/@vueuse+integrations@10.11.0_focus-trap@7.5.4_sortablejs@1.15.2_vue@3.4.29/node_modules/@vueuse/integrations/useFocusTrap.mjs",
      "file": "vitepress___@vueuse_integrations_useFocusTrap.js",
      "fileHash": "90c0fe13",
      "needsInterop": false
    },
    "vitepress > mark.js/src/vanilla.js": {
      "src": "../../../../node_modules/.pnpm/mark.js@8.11.1/node_modules/mark.js/src/vanilla.js",
      "file": "vitepress___mark__js_src_vanilla__js.js",
      "fileHash": "14e355df",
      "needsInterop": false
    },
    "vitepress > minisearch": {
      "src": "../../../../node_modules/.pnpm/minisearch@6.3.0/node_modules/minisearch/dist/es/index.js",
      "file": "vitepress___minisearch.js",
      "fileHash": "df7a48ef",
      "needsInterop": false
    },
    "@vitepress-demo-preview/component": {
      "src": "../../../../node_modules/.pnpm/@vitepress-demo-preview+component@2.3.2_vitepress@1.2.3_@algolia+client-search@4.23.3_@types+_jfkbc7v6jq6t7s7n62i7mta6om/node_modules/@vitepress-demo-preview/component/dist/preview-component.js",
      "file": "@vitepress-demo-preview_component.js",
      "fileHash": "35138841",
      "needsInterop": false
    },
    "lodash-es": {
      "src": "../../../../node_modules/.pnpm/lodash-es@4.17.21/node_modules/lodash-es/lodash.js",
      "file": "lodash-es.js",
      "fileHash": "9475b6da",
      "needsInterop": false
    },
    "tdesign-vue-next": {
      "src": "../../../../node_modules/.pnpm/tdesign-vue-next@1.9.6_vue@3.4.29/node_modules/tdesign-vue-next/es/index.mjs",
      "file": "tdesign-vue-next.js",
      "fileHash": "6425606c",
      "needsInterop": false
    },
    "tdesign-icons-vue-next": {
      "src": "../../../../node_modules/.pnpm/tdesign-icons-vue-next@0.2.2_vue@3.4.29/node_modules/tdesign-icons-vue-next/esm/index.js",
      "file": "tdesign-icons-vue-next.js",
      "fileHash": "e3e99cea",
      "needsInterop": false
    }
  },
  "chunks": {
    "chunk-KCM3TZIG": {
      "file": "chunk-KCM3TZIG.js"
    },
    "chunk-U57OPSL7": {
      "file": "chunk-U57OPSL7.js"
    },
    "chunk-PPTVPZ73": {
      "file": "chunk-PPTVPZ73.js"
    }
  }
}